[
  {
    "department": "Art -Ceramics",
    "program": "Art -Ceramics",
    "years": [
      {
        "year": "First Year",
        "semesters": [
          {
            "semester": "Fall",
            "courses": [
              {
                "hours": 3,
                "courseNumber": "Choose 1",
                "title": "Communication (Core)",
                "minGrade": "C",
                "gec": "010",
                "prerequisite": "",
                "notes": "For all 010 courses: Satisfactory scores on English portion of ACT test and TSI examination or ENGL 0301. For ENGL 1302, a grade of 'C' or better in ENGL 1301. See General Education Core for more details. Options: ENGL 1301"
              },
              {
                "hours": 3,
                "courseNumber": "ARTS 1303 or 1304",
                "title": "Art History I or Art History II",
                "minGrade": "",
                "gec": "050",
                "prerequisite": "",
                "notes": "Satisfies General Education Core."
              },
              {
                "hours": 3,
                "courseNumber": "ARTS 1311",
                "title": "2D Foundations",
                "minGrade": "",
                "gec": "",
                "prerequisite": "",
                "notes": "Satisfies Major-Specific Requirement."
              },
              {
                "hours": 3,
                "courseNumber": "ARTS 1316",
                "title": "Drawing I",
                "minGrade": "",
                "gec": "",
                "prerequisite": "",
                "notes": "Satisfies Major-Specific Requirement."
              },
              {
                "hours": 3,
                "courseNumber": "POLS 2305",
                "title": "U.S. Federal Govt & Politics",
                "minGrade": "",
                "gec": "070",
                "prerequisite": "",
                "notes": ""
              },
              {
                "hours": 0,
                "courseNumber": "UNIV 1301",
                "title": "Learning Framework",
                "minGrade": "",
                "gec": "",
                "prerequisite": "",
                "notes": "As required, based on credit hours earned, TSI status, High school rank, major declaration."
              }
            ]
          },
          {
            "semester": "Spring",
            "courses": [
              {
                "hours": 3,
                "courseNumber": "Choose 1",
                "title": "Communication (Core)",
                "minGrade": "C",
                "gec": "010",
                "prerequisite": "",
                "notes": "For all 010 courses: Satisfactory scores on English portion of ACT test and TSI examination or ENGL 0301. For ENGL 1302, a grade of 'C' or better in ENGL 1301. See General Education Core for more details. Options: ENGL 1302 or ENGL 1305"
              },
              {
                "hours": 3,
                "courseNumber": "Choose 1",
                "title": "American History (Core)",
                "minGrade": "",
                "gec": "060",
                "prerequisite": "",
                "notes": "See General Education Core for more details. Options: HIST 1301 or HIST 2327"
              },
              {
                "hours": 3,
                "courseNumber": "Choose 1",
                "title": "Mathematics (Core)",
                "minGrade": "C",
                "gec": "020",
                "prerequisite": "College Ready TSI status in Mathematics.",
                "notes": "See General Education Core for course options. MATH 1314 or higher recommended."
              },
              {
                "hours": 3,
                "courseNumber": "ARTS 1312",
                "title": "3D Foundations",
                "minGrade": "",
                "gec": "",
                "prerequisite": "",
                "notes": "Satisfies Major-Specific Requirement."
              },
              {
                "hours": 3,
                "courseNumber": "ARTS 1317",
                "title": "Drawing II",
                "minGrade": "",
                "gec": "",
                "prerequisite": "",
                "notes": "Satisfies Major-Specific Requirement."
              }
            ]
          }
        ]
      },
      {
        "year": "Second Year",
        "semesters": [
          {
            "semester": "Fall",
            "courses": [
              {
                "hours": 3,
                "courseNumber": "Choose 1",
                "title": "American History (Core)",
                "minGrade": "",
                "gec": "060",
                "prerequisite": "",
                "notes": "See General Education Core for more details. Options: HIST 1302 or HIST 2328"
              },
              {
                "hours": 4,
                "courseNumber": "Choose 1",
                "title": "Life and Physical Sciences (Core)",
                "minGrade": "",
                "gec": "030",
                "prerequisite": "",
                "notes": "May apply pending course selection. See General Education Core for course options. 1 credit hour of lab may apply to category 090."
              },
              {
                "hours": 3,
                "courseNumber": "ARTS 2346",
                "title": "Ceramics I",
                "minGrade": "C",
                "gec": "",
                "prerequisite": "",
                "notes": "Satisfies Ceramics Concentration."
              },
              {
                "hours": 3,
                "courseNumber": "ARTS 1303 or 1304",
                "title": "Art History I or Art History II",
                "minGrade": "",
                "gec": "",
                "prerequisite": "",
                "notes": "ARTS 1303 and ARTS 1304 must both be completed. One will be applied to the core curriculum, the other to the major requirements."
              },
              {
                "hours": 3,
                "courseNumber": "ARTS X3XX",
                "title": "3D Art Elective",
                "minGrade": "",
                "gec": "",
                "prerequisite": "",
                "notes": "See Degree Plan for course options. Choose 1 from 3D Art category."
              }
            ]
          },
          {
            "semester": "Spring",
            "courses": [
              {
                "hours": 3,
                "courseNumber": "Choose 1",
                "title": "Language, Philosophy & Culture (Core)",
                "minGrade": "",
                "gec": "040",
                "prerequisite": "",
                "notes": "See General Education Core for course options."
              },
              {
                "hours": 4,
                "courseNumber": "Choose 1",
                "title": "Life and Physical Sciences (Core)",
                "minGrade": "",
                "gec": "030",
                "prerequisite": "",
                "notes": "May apply pending course selection. See General Education Core for course options. 1 credit hour of lab may apply to category 090."
              },
              {
                "hours": 3,
                "courseNumber": "ARTS X3XX",
                "title": "3D Art Elective",
                "minGrade": "",
                "gec": "",
                "prerequisite": "",
                "notes": "See Degree Plan for course options. Choose 1 from 3D Art category."
              },
              {
                "hours": 3,
                "courseNumber": "ARTS 33XX-43XX",
                "title": "Studio Art Advanced Elective",
                "minGrade": "",
                "gec": "",
                "prerequisite": "",
                "notes": "See Degree Plan for course options."
              },
              {
                "hours": 3,
                "courseNumber": "ARTS 335X-435X",
                "title": "Art History Advanced Elective",
                "minGrade": "",
                "gec": "",
                "prerequisite": "",
                "notes": "See Degree Plan for course options."
              }
            ]
          }
        ]
      },
      {
        "year": "Third Year",
        "semesters": [
          {
            "semester": "Fall",
            "courses": [
              {
                "hours": 3,
                "courseNumber": "POLS 2306",
                "title": "Texas Government & Politics",
                "minGrade": "",
                "gec": "070",
                "prerequisite": "",
                "notes": ""
              },
              {
                "hours": 3,
                "courseNumber": "ARTS 33XX-43XX",
                "title": "3D Art Elective",
                "minGrade": "",
                "gec": "",
                "prerequisite": "",
                "notes": "See Degree Plan for course options. Choose 1 from 3D Art category."
              },
              {
                "hours": 3,
                "courseNumber": "ARTS 3311",
                "title": "Intermediate Drawing",
                "minGrade": "",
                "gec": "",
                "prerequisite": "Grade of C or better in ARTS 1317.",
                "notes": "Satisfies Major-Specific Requirement."
              },
              {
                "hours": 3,
                "courseNumber": "ARTS 33XX-43XX",
                "title": "Ceramics Concentration",
                "minGrade": "C",
                "gec": "",
                "prerequisite": "",
                "notes": "See Degree Plan for course options."
              },
              {
                "hours": 3,
                "courseNumber": "ARTS 33XX-43XX",
                "title": "Studio Art Advanced Elective",
                "minGrade": "",
                "gec": "",
                "prerequisite": "",
                "notes": "See Degree Plan for course options."
              },
              {
                "hours": 3,
                "courseNumber": "ARTS 335X-435X",
                "title": "Art History Advanced Elective",
                "minGrade": "",
                "gec": "",
                "prerequisite": "",
                "notes": "See Degree Plan for course options."
              }
            ]
          },
          {
            "semester": "Spring",
            "courses": [
              {
                "hours": 3,
                "courseNumber": "ARTS 335X-435X",
                "title": "Art History Advanced Elective",
                "minGrade": "",
                "gec": "",
                "prerequisite": "",
                "notes": "See Degree Plan for course options."
              },
              {
                "hours": 3,
                "courseNumber": "ARTS 33XX-43XX",
                "title": "3D Art Elective",
                "minGrade": "",
                "gec": "",
                "prerequisite": "",
                "notes": "See Degree Plan for course options. Choose 1 from 3D Art category."
              },
              {
                "hours": 3,
                "courseNumber": "ARTS 33XX-43XX",
                "title": "Ceramics Concentration",
                "minGrade": "C",
                "gec": "",
                "prerequisite": "",
                "notes": "See Degree Plan for course options."
              },
              {
                "hours": 3,
                "courseNumber": "ARTS 33XX-43XX",
                "title": "Studio Art Advanced Elective",
                "minGrade": "",
                "gec": "",
                "prerequisite": "",
                "notes": "See Degree Plan for course options."
              },
              {
                "hours": 3,
                "courseNumber": "Choose 1",
                "title": "Integrative/Experimental Learning Option (Core)",
                "minGrade": "",
                "gec": "090",
                "prerequisite": "",
                "notes": "See General Education Core for course options."
              }
            ]
          }
        ]
      },
      {
        "year": "Fourth Year",
        "semesters": [
          {
            "semester": "Fall",
            "courses": [
              {
                "hours": 3,
                "courseNumber": "Choose 1",
                "title": "Social and Behavioral Sciences (Core)",
                "minGrade": "",
                "gec": "080",
                "prerequisite": "",
                "notes": "See General Education Core for course options."
              },
              {
                "hours": 1,
                "courseNumber": "Choose 1",
                "title": "Integrative/Experimental Learning Option (Core)",
                "minGrade": "",
                "gec": "090",
                "prerequisite": "",
                "notes": "See General Education Core for course options."
              },
              {
                "hours": 3,
                "courseNumber": "ARTS 33XX-43XX",
                "title": "Ceramics Concentration",
                "minGrade": "C",
                "gec": "",
                "prerequisite": "",
                "notes": "See Degree Plan for course options."
              },
              {
                "hours": 3,
                "courseNumber": "ARTS 33XX-43XX",
                "title": "Studio Art Advanced Elective",
                "minGrade": "",
                "gec": "",
                "prerequisite": "",
                "notes": "See Degree Plan for course options."
              },
              {
                "hours": 3,
                "courseNumber": "ARTS 33XX-43XX",
                "title": "Ceramics Concentration",
                "minGrade": "C",
                "gec": "",
                "prerequisite": "",
                "notes": "See Degree Plan for course options."
              }
            ]
          },
          {
            "semester": "Spring",
            "courses": [
              {
                "hours": 3,
                "courseNumber": "ARTS 4340",
                "title": "Portfolio for Studio Art",
                "minGrade": "",
                "gec": "",
                "prerequisite": "Student must be of Senior standing.",
                "notes": "Satisfies Major-Specific Requirement."
              },
              {
                "hours": 3,
                "courseNumber": "ARTS 4397",
                "title": "BFA Exhibit in Studio Art (Capstone)",
                "minGrade": "C",
                "gec": "",
                "prerequisite": "Student must be of Senior standing.",
                "notes": "Satisfies Major-Specific Requirement."
              },
              {
                "hours": 3,
                "courseNumber": "ARTS 33XX-43XX",
                "title": "Studio Art Advanced Elective",
                "minGrade": "",
                "gec": "",
                "prerequisite": "",
                "notes": "See Degree Plan for course options."
              },
              {
                "hours": 3,
                "courseNumber": "13XX-43XX",
                "title": "Free Elective",
                "minGrade": "C",
                "gec": "",
                "prerequisite": "",
                "notes": "See Degree Plan for course options."
              }
            ]
          }
        ]
      }
    ]
  }
]
